mcrconpy/__init__.py
mcrconpy/audit.py
mcrconpy/authn.py
mcrconpy/cli.py
mcrconpy/connection.py
mcrconpy/controller.py
mcrconpy/exceptions.py
mcrconpy/models.py
mcrconpy/packet.py
mcrconpy/pathclass.py
mcrconpy/utils.py
mcrconpy/version.py
mcrconpy-0.1.1.dist-info/LICENSE
mcrconpy-0.1.1.dist-info/METADATA
mcrconpy-0.1.1.dist-info/WHEEL
mcrconpy-0.1.1.dist-info/entry_points.txt
mcrconpy-0.1.1.dist-info/RECORD
