Metadata-Version: 2.3
Name: mcrconpy
Version: 0.1.1
Summary: RCON protocol client for the Minecraft server.
License: MIT
Keywords: rcon,remote console
Author: kurotom
Author-email: 55354389+kurotom@users.noreply.github.com
Requires-Python: >=3.9,<4.0
Classifier: Operating System :: OS Independent
Classifier: Programming Language :: Python :: 3.9
Classifier: Programming Language :: Python :: 3.10
Classifier: Programming Language :: Python :: 3.11
Classifier: Programming Language :: Python :: 3.12
Requires-Dist: platformdirs (>=4.3.8,<5.0.0)
Project-URL: Bug Tracker, https://github.com/kurotom/mcrconpy/issues
